cryodrgn/__init__.py
cryodrgn/bibtex.py
cryodrgn/constants.py
cryodrgn/cryodrgn_logo.png
cryodrgn/protocols.conf
cryodrgn/utils.py
cryodrgn/viewers.py
cryodrgn/protocols/__init__.py
cryodrgn/protocols/protocol_abinitio.py
cryodrgn/protocols/protocol_analyze.py
cryodrgn/protocols/protocol_base.py
cryodrgn/protocols/protocol_preprocess.py
cryodrgn/protocols/protocol_subset.py
cryodrgn/protocols/protocol_train.py
cryodrgn/tests/__init__.py
cryodrgn/tests/test_protocols_cryodrgn.py
scipion_em_cryodrgn-3.13.1.dist-info/LICENSE
scipion_em_cryodrgn-3.13.1.dist-info/METADATA
scipion_em_cryodrgn-3.13.1.dist-info/WHEEL
scipion_em_cryodrgn-3.13.1.dist-info/entry_points.txt
scipion_em_cryodrgn-3.13.1.dist-info/top_level.txt
scipion_em_cryodrgn-3.13.1.dist-info/RECORD
